<?xml version="1.0" encoding="utf-8" ?><dwsync><file name="highlight.png" server="192.168.10.103//var/www/modelspot/" local="3435758044" remote="318763443832826861" Dst="-1" /><file name="glass.png" server="192.168.10.103//var/www/modelspot/" local="3435758044" remote="318763443832826894" Dst="-1" /><file name="glass-lighter.png" server="192.168.10.103//var/www/modelspot/" local="3435758044" remote="318763443832826894" Dst="-1" /><file name="brushed-metal.png" server="192.168.10.103//var/www/modelspot/" local="3435758044" remote="318763443832826895" Dst="-1" /><file name="dots1.png" server="192.168.10.103//var/www/modelspot/" local="3435758044" remote="318763443832826896" Dst="-1" /><file name="dots10.png" server="192.168.10.103//var/www/modelspot/" local="3435758044" remote="318763443832826896" Dst="-1" /><file name="dots11.png" server="192.168.10.103//var/www/modelspot/" local="3435758044" remote="318763443832826896" Dst="-1" /><file name="dots12.png" server="192.168.10.103//var/www/modelspot/" local="3435758044" remote="318763443832826896" Dst="-1" /><file name="dots13.png" server="192.168.10.103//var/www/modelspot/" local="3435758044" remote="318763443832826896" Dst="-1" /><file name="dots2.png" server="192.168.10.103//var/www/modelspot/" local="3435758044" remote="318763443832826896" Dst="-1" /><file name="dots3.png" server="192.168.10.103//var/www/modelspot/" local="3435758044" remote="318763443832826896" Dst="-1" /><file name="dots4.png" server="192.168.10.103//var/www/modelspot/" local="3435758044" remote="318763443832826896" Dst="-1" /><file name="dots5.png" server="192.168.10.103//var/www/modelspot/" local="3435758044" remote="318763443832826896" Dst="-1" /><file name="dots6.png" server="192.168.10.103//var/www/modelspot/" local="3435758044" remote="318763443832826896" Dst="-1" /><file name="dots7.png" server="192.168.10.103//var/www/modelspot/" local="3435758044" remote="318763443832826896" Dst="-1" /><file name="dots8.png" server="192.168.10.103//var/www/modelspot/" local="3435758044" remote="318763443832826896" Dst="-1" /><file name="dots9.png" server="192.168.10.103//var/www/modelspot/" local="3435758044" remote="318763443832826896" Dst="-1" /><file name="leather1.png" server="192.168.10.103//var/www/modelspot/" local="3435758044" remote="318763443832826896" Dst="-1" /><file name="leather2.png" server="192.168.10.103//var/www/modelspot/" local="3435758044" remote="318763443832826896" Dst="-1" /><file name="noise.png" server="192.168.10.103//var/www/modelspot/" local="3435758044" remote="318763443832826896" Dst="-1" /><file name="stripe1.png" server="192.168.10.103//var/www/modelspot/" local="3435758044" remote="318763443832826896" Dst="-1" /><file name="stripe2.png" server="192.168.10.103//var/www/modelspot/" local="3435758044" remote="318763443832826896" Dst="-1" /><file name="stripe3.png" server="192.168.10.103//var/www/modelspot/" local="3435758044" remote="318763443832826896" Dst="-1" /><file name="stripe4.png" server="192.168.10.103//var/www/modelspot/" local="3435758044" remote="318763443832826896" Dst="-1" /><file name="stripe5.png" server="192.168.10.103//var/www/modelspot/" local="3435758044" remote="318763443832826896" Dst="-1" /><file name="stripe6.png" server="192.168.10.103//var/www/modelspot/" local="3435758044" remote="318763443832826896" Dst="-1" /><file name="highlight.png" server="192.168.0.107//var/www/modelspot/" local="3435758044" remote="318763443832888636" Dst="-1" /><file name="highlight.png" server="192.168.0.133//var/www/modelspot/" local="3435758044" remote="318763443833058938" Dst="-1" /><file name="highlight.png" server="192.168.10.101//var/www/factav2/" local="3435758044" remote="318763443833857809" Dst="-1" /><file name="glass.png" server="192.168.10.101//var/www/factav2/" local="3435758044" remote="318763443833857827" Dst="-1" /><file name="glass-lighter.png" server="192.168.10.101//var/www/factav2/" local="3435758044" remote="318763443833857827" Dst="-1" /><file name="brushed-metal.png" server="192.168.10.101//var/www/factav2/" local="3435758044" remote="318763443833857828" Dst="-1" /><file name="dots1.png" server="192.168.10.101//var/www/factav2/" local="3435758044" remote="318763443833857829" Dst="-1" /><file name="dots10.png" server="192.168.10.101//var/www/factav2/" local="3435758044" remote="318763443833857829" Dst="-1" /><file name="dots11.png" server="192.168.10.101//var/www/factav2/" local="3435758044" remote="318763443833857829" Dst="-1" /><file name="dots12.png" server="192.168.10.101//var/www/factav2/" local="3435758044" remote="318763443833857829" Dst="-1" /><file name="dots13.png" server="192.168.10.101//var/www/factav2/" local="3435758044" remote="318763443833857829" Dst="-1" /><file name="dots2.png" server="192.168.10.101//var/www/factav2/" local="3435758044" remote="318763443833857829" Dst="-1" /><file name="dots3.png" server="192.168.10.101//var/www/factav2/" local="3435758044" remote="318763443833857829" Dst="-1" /><file name="dots4.png" server="192.168.10.101//var/www/factav2/" local="3435758044" remote="318763443833857829" Dst="-1" /><file name="dots5.png" server="192.168.10.101//var/www/factav2/" local="3435758044" remote="318763443833857829" Dst="-1" /><file name="dots6.png" server="192.168.10.101//var/www/factav2/" local="3435758044" remote="318763443833857829" Dst="-1" /><file name="dots7.png" server="192.168.10.101//var/www/factav2/" local="3435758044" remote="318763443833857829" Dst="-1" /><file name="dots8.png" server="192.168.10.101//var/www/factav2/" local="3435758044" remote="318763443833857829" Dst="-1" /><file name="dots9.png" server="192.168.10.101//var/www/factav2/" local="3435758044" remote="318763443833857829" Dst="-1" /><file name="leather1.png" server="192.168.10.101//var/www/factav2/" local="3435758044" remote="318763443833857829" Dst="-1" /><file name="leather2.png" server="192.168.10.101//var/www/factav2/" local="3435758044" remote="318763443833857829" Dst="-1" /><file name="noise.png" server="192.168.10.101//var/www/factav2/" local="3435758044" remote="318763443833857829" Dst="-1" /><file name="stripe1.png" server="192.168.10.101//var/www/factav2/" local="3435758044" remote="318763443833857829" Dst="-1" /><file name="stripe2.png" server="192.168.10.101//var/www/factav2/" local="3435758044" remote="318763443833857829" Dst="-1" /><file name="stripe3.png" server="192.168.10.101//var/www/factav2/" local="3435758044" remote="318763443833857829" Dst="-1" /><file name="stripe4.png" server="192.168.10.101//var/www/factav2/" local="3435758044" remote="318763443833857829" Dst="-1" /><file name="stripe5.png" server="192.168.10.101//var/www/factav2/" local="3435758044" remote="318763443833857829" Dst="-1" /><file name="stripe6.png" server="192.168.10.101//var/www/factav2/" local="3435758044" remote="318763443833857829" Dst="-1" /></dwsync>